ftd_api/__init__.py
ftd_api/bulk_tool.py
ftd_api/file_helper.py
ftd_api/ftd_client.py
ftd_api/logging.py
ftd_api/parse_csv.py
ftd_api/parse_json.py
ftd_api/parse_properties.py
ftd_api/parse_yaml.py
ftd_api/string_helper.py
ftd_api-0.0.8.data/scripts/ftd_bulk_tool
ftd_api-0.0.8.data/scripts/ftd_bulk_tool.py
ftd_api-0.0.8.dist-info/LICENSE.txt
ftd_api-0.0.8.dist-info/METADATA
ftd_api-0.0.8.dist-info/WHEEL
ftd_api-0.0.8.dist-info/top_level.txt
ftd_api-0.0.8.dist-info/RECORD
