Metadata-Version: 2.1
Name: ftd-api
Version: 0.0.8
Summary: Useful tooling for the Firepower Threat Defense on-box REST API
Home-page: https://github.com/jaredtsmith/ftd_api
Author: Jared T. Smith
Author-email: jarsmith@cisco.com
License: UNKNOWN
Project-URL: Source, https://github.com/jaredtsmith/ftd_api
Project-URL: FTD API Reference, https://developer.cisco.com/site/ftd_api-reference/
Project-URL: Firepower DEVNET Portal, https://developer.cisco.com/firepower/
Project-URL: Firepower Product Information, https://www.cisco.com/c/en/us/products/security/firewalls/index.html
Keywords: cisco firepower ftd ngfw rest api
Platform: UNKNOWN
Classifier: Development Status :: 3 - Alpha
Classifier: Programming Language :: Python :: 3
Classifier: Programming Language :: Python :: 3.6
Classifier: Programming Language :: Python :: 3.7
Classifier: License :: OSI Approved :: MIT License
Classifier: Operating System :: OS Independent
Requires-Python: >=3.6
Requires-Dist: pyaml (>=19.12.0)
Requires-Dist: requests (>=2.22.0)
Requires-Dist: coloredlogs (>=10.0)
